{"img/me.png": true, "baobab/schema.txt": true, "img/zip.png": true, "baobab/.git/logs/refs/remotes/origin/HEAD": true, "dev/mud.tilde.town/ud-game-standard-scenery.py.png": true, "dev/mud.tilde.town/ud-core-components-core.py.png": true, "dev/mud.tilde.town/ud-game-standard-container-core.py.png": true, "public.json": true, "img/icon-folder.png": true, "dev/mud.tilde.town/ud-login.py.png": true, "dev/mud.tilde.town/ud-game-standard-thing.py.png": true, "dev/mud.tilde.town/-irc.py.png": true, "dev/mud.tilde.town/ud-game-people.py.png": true, "baobab/index.html": true, "writing/nothing": true, "dev/mud.tilde.town/ud-core-dispatch-__init__.py.png": true, "img/portege610ct.jpg": true, "dev/mud.tilde.town/ud-core-parse-dice.py.png": true, "baobab/.git/refs/heads/selfsame": true, "js/libs/jquery-1.7.1.min.js": true, "dev/mud.tilde.town/ud-game-standard-room.py.png": true, "dev/mud.tilde.town/-colors.py.png": true, "dev/sameself.py": true, "baobab/baobab.css": true, "baobab/.git/logs/refs/heads/master": true, "dev/mud.tilde.town/ud-core-__init__.py.png": true, "dev/mud.tilde.town/ud-game-standard-description-__init__.py.png": true, "dev/mud.tilde.town/ud-core-parse-__init__.py.png": true, "baobab/.git/objects/a4/b229b963f5b9d49a1178a61cc6522c202b0ec7": true, "writing/inform7/space_command.txt": true, "dev/mud.tilde.town/ud-game-standard-player-verbs.py.png": true, "js/libs/jquery-1.7.1.js": true, "baobab/.git/refs/remotes/origin/HEAD": true, "img/img.png": true, "baobab/.git/hooks/pre-applypatch.sample": true, "baobab/.gitignore": true, "img/icon-image.png": true, "baobab/.git/hooks/update.sample": true, "dev/mud.tilde.town/ud-core-components-__init__.py.png": true, "css/style.css": true, "dev/mud.tilde.town/ud-game-standard-entity.py.png": true, "dev/mud.tilde.town/ud-game-standard-grammar.py.png": true, "dev/mud.tilde.town/-hello.hs.png": true, "dev/mud.tilde.town/ud-game-standard-world.py.png": true, "writing/notes.txt": true, "dev/mud.tilde.town/ud-core-colors.py.png": true, "baobab/story.bb": true, "writing/inform7/dungeon_planet.txt": true, "baobab/.git/info/exclude": true, "dev/mud.tilde.town/-game.hs.png": true, "baobab/.git/hooks/commit-msg.sample": true, "baobab/.git/refs/remotes/origin/master": true, "img/window-bar.png": true, "baobab/.git/hooks/prepare-commit-msg.sample": true, "dev/basic.html": true, "img/1bithalftone.png": true, "dev/mud.tilde.town/ud-core-bind.py.png": true, "dev/mud.tilde.town/ud-game-coloration.py.png": true, "dev/mud.tilde.town/ud-core-data.py.png": true, "dev/mud.tilde.town/-telnet.hs.png": true, "dev/mud.tilde.town/ud-core-CAPSMODE.py.png": true, "dev/mud.tilde.town/ud-game-standard-container-__init__.py.png": true, "baobab/.git/hooks/pre-push.sample": true, "baobab/baobab.rkt": true, "dev/mud.tilde.town/ud-game-standard-player-__init__.py.png": true, "dev/mud.tilde.town/ud-game-standard-__init__.py.png": true, "dev/mud.tilde.town/ud-game-standard-player-actions.py.png": true, "dev/mud.tilde.town/ud-core-verbs.py.png": true, "baobab/.git/hooks/post-update.sample": true, "baobab/.git/packed-refs": true, "colors.zip": true, "writing/birdfacts.html": true, "baobab/rivergods.bb": true, "dev/mud.tilde.town/ud-game-standard-description-listing.py.png": true, "dev/mud.tilde.town/ud-game-standard-player-input.py.png": true, "dev/mud.tilde.town/ud-game-standard-dialogue.py.png": true, "baobab/.git/description": true, "dev/mud.tilde.town/ud-game-__init__.py.png": true, "baobab/.git/hooks/pre-rebase.sample": true, "dev/mud.tilde.town/python-irc.py.png": true, "dev/mud.tilde.town/ud-game-admin.py.png": true, "baobab/.git/logs/HEAD": true, "baobab/LICENSE.txt": true, "baobab/README.md": true, "dev/mud.tilde.town/ud-game-combat.py.png": true, "baobab/.git/objects/pack/pack-db53e030314dd43031311cd0f4fd914834576618.idx": true, "img/angband.jpg": true, "img/colors.png": true, "dev/mud.tilde.town/ud-game-standard-description-rooms.py.png": true, "dev/mud.tilde.town/-fig.py.png": true, "index.html": true, "dev/mud.tilde.town/ud-core-dispatch-core.py.png": true, "img/this.png": true, "dev/mud.tilde.town/ud-core-parse-mttlang.py.png": true, "baobab/.git/logs/refs/remotes/origin/master": true, "baobab/.git/index": true, "js/script.js": true, "dev/mud.tilde.town/ud-game-standard-player-core.py.png": true, "dev/mud.tilde.town/ud-core-dialogue.py.png": true, "dev/mud.tilde.town/-server.py.png": true, "dev/mud.tilde.town/result.html": true, "baobab/.git/HEAD": true, "baobab/baobab.js": true, "baobab/.git/objects/df/1925c19e0e65ea3df0c36a28cc44f51634aa39": true, "baobab/.git/config": true, "baobab/rivergods.json": true, "dev/mud.tilde.town/ud-core-util.py.png": true, "baobab/.git/objects/58/abda307922a6d9211fa898f73ec6f737d1c653": true, "dev/mud.tilde.town/ud-core-predicates.py.png": true, "baobab/.git/objects/pack/pack-db53e030314dd43031311cd0f4fd914834576618.pack": true, "baobab/.git/logs/refs/heads/selfsame": true, "baobab/.git/hooks/pre-commit.sample": true, "dev/mud.tilde.town/ud-game-standard-basic.py.png": true, "img/rating2.gif": true, "dev/mud.tilde.town/ud-game-writing.py.png": true, "MUD/leaderboard.html": true, "baobab/.git/hooks/applypatch-msg.sample": true, "dev/mud.tilde.town/-tweet.py.png": true, "baobab/.git/FETCH_HEAD": true, "dev/mud.tilde.town/ud-core-context.py.png": true, "dev/mud.tilde.town/python-tweet.py.png": true, "dev/mud.tilde.town/ud-__init__.py.png": true, "mastodonbots.html": true, "web.html": true, "img/icon-doc.png": true, "welcome.html": true, "baobab/.git/ORIG_HEAD": true, "baobab/.git/refs/heads/master": true, "dev/mud.tilde.town/python-colors.py.png": true, "dev/mud.tilde.town/ud-game-standard-scope.py.png": true, "dev/mud.tilde.town/python-fig.py.png": true}